myCalculatorPackage/__init__.py
myCalculatorPackage/division/__init__.py
myCalculatorPackage/division/divide.py
myCalculatorPackage/multiplication/__init__.py
myCalculatorPackage/multiplication/multiply.py
myCalculatorPackage-0.0.2.dist-info/LICENSE.txt
myCalculatorPackage-0.0.2.dist-info/METADATA
myCalculatorPackage-0.0.2.dist-info/WHEEL
myCalculatorPackage-0.0.2.dist-info/top_level.txt
myCalculatorPackage-0.0.2.dist-info/RECORD
