Metadata-Version: 2.1
Name: myCalculatorPackage
Version: 0.0.2
Summary: An example package
Author-email: Khalad Hasan <khalad.hasan@gmail.com>
Project-URL: Homepage, https://github.com/khalad-hasan/myCalculatorPackage
Project-URL: Issues, https://github.com/khalad-hasan/myCalculatorPackage/issues
Classifier: Programming Language :: Python :: 3
Classifier: License :: OSI Approved :: MIT License
Classifier: Operating System :: OS Independent
Requires-Python: >=3.8
License-File: LICENSE.txt
